{
  "name": "Flora Parsons",
  "age": 54,
  "address": {
    "street": "Kavum Extension",
    "city": "Obobigan",
    "state": "OR",
    "zip": "74679"
  },
  "contact": {
    "phone": "(725) 859-8973",
    "servicePhone": "800483296"
  },
  "birthday": "1975-12-25T02:04:15.810Z",
  "ip": "136.31.117.50",
  "foo": "bar",
  "profile": {
    "about": "Ceokagaw upo mu ulalcu heazci poji sihemo fu gohpilir zozbize dujmiet wez uwocoaju ode ofetot. Iscujobu oztuog facmu vabfa dud uhavu fad vijad acsonal idi anwedmun woku. Sohakedob vi gu ozuukwi juwij za zadsosuc ephehi ufo fabiana padjev apbo. Epalu of sap suzgo pi sasha tewlitsa cowilido ebfihdu hihe hofobuj zomuwdef paaw. Jusnomo ig ca gikhaz afuoku ri api dozej lope zabkutes ewejewi na tieh iv mecakoh zazek kew. Isabaof faz wefda duwug zodiv opnatose fopkom gemza duwigpuf uhbij jah ebiutu.",
    "bio": "Pesabdi tiove ok zakzozba kesesuf elke wewigmef zulliw mihtokde ijsan ob mid duz nebiwmib lateahu pi. Javbih ve wajba bakgu ufordim ragaf duzi zamez dozelik sum go te puremjuc hifhorha. Ewutuj zitcare efa now noviwnuv gikimva seatu ceg maw jifozaon putov sawmojab ulito buwhac aluzegfum wuapo. Hupoh ewave timuvo toru vu gu su niflevut iv bemerero ogwozpem avwide ginpomkif nanis viritos."
  },
  "apiKey": "23c4f46d2a1de21f2c902e108a36921930dd487a54ac6a6e58edfec346c68f89",
  "currency": {
    "code": "DOP",
    "name": "Dominican Republic Peso"
  }
}